{
  "productName": "angular-electron",
  "directories": {
    "buildResources": "resources",
    "output": "release/"
  },
  "files": [
    "**/*",
    "./resources/**/*",
    "!**/*.ts",
    "!.github",
    "!.vscode",
    "!.code-workspace",
    "!.npmrc",
    "!*.md",
    "!package.json",
    "!package-lock.json",
    "!src/",
    "!e2e/",
    "!hooks/",
    "!_config.yml",
    "!angular.json",
    "!tsconfig*.json",
    "!tslint.json",
    "!.eslintrc.json",
    "!karma.conf.js",
    "!angular.webpack.js",
    "!*.map"
  ],
  "win": {
    "icon": "dist/assets/icons",
    "target": ["portable"]
  },
  "portable": {
    "splashImage": "dist/assets/icons/electron.bmp"
  },
  "mac": {
    "icon": "dist/assets/icons",
    "target": ["dmg"]
  },
  "linux": {
    "icon": "resources/icons/icon.png",
    "target": ["AppImage"]
  },
  "extraFiles": [
    "resources/*"
  ]
}
